CHANGES.txt
MANIFEST.in
README.txt
setup.py
js/__init__.py
js.jquery_autosize.egg-info/PKG-INFO
js.jquery_autosize.egg-info/SOURCES.txt
js.jquery_autosize.egg-info/dependency_links.txt
js.jquery_autosize.egg-info/entry_points.txt
js.jquery_autosize.egg-info/namespace_packages.txt
js.jquery_autosize.egg-info/not-zip-safe
js.jquery_autosize.egg-info/requires.txt
js.jquery_autosize.egg-info/top_level.txt
js/jquery_autosize/__init__.py
js/jquery_autosize/test_jquery_autosize.txt
js/jquery_autosize/resources/jquery.autosize.js
js/jquery_autosize/resources/jquery.autosize.min.js