Metadata-Version: 1.0
Name: js.jquery-autosize
Version: 1.17.1
Summary: fanstatic jQuery autosize.
Home-page: UNKNOWN
Author: Thomas Massmann
Author-email: thomas.massmann@it-spir.it
License: BSD
Platform: UNKNOWN
